numbergen/__init__.py
param/.version
param/__init__.py
param/_async.py
param/ipython.py
param/parameterized.py
param/serializer.py
param/version.py
param-1.13.0.dist-info/LICENSE.txt
param-1.13.0.dist-info/METADATA
param-1.13.0.dist-info/WHEEL
param-1.13.0.dist-info/top_level.txt
param-1.13.0.dist-info/RECORD
