Metadata-Version: 2.1
Name: param
Version: 1.13.0
Summary: Make your Python code clearer and more reliable by declaring Parameters.
Home-page: http://param.holoviz.org/
Author: HoloViz
Author-email: developers@holoviz.org
Maintainer: HoloViz
Maintainer-email: developers@holoviz.org
License: BSD
Project-URL: Documentation, https://param.holoviz.org/
Project-URL: Releases, https://github.com/holoviz/param/releases
Project-URL: Bug Tracker, https://github.com/holoviz/param/issues
Project-URL: Source Code, https://github.com/holoviz/param
Project-URL: Panel Examples, https://panel.holoviz.org/user_guide/Param.html
Platform: Windows
Platform: Mac OS X
Platform: Linux
Classifier: License :: OSI Approved :: BSD License
Classifier: Development Status :: 5 - Production/Stable
Classifier: Programming Language :: Python :: 2
Classifier: Programming Language :: Python :: 2.7
Classifier: Programming Language :: Python :: 3
Classifier: Programming Language :: Python :: 3.6
Classifier: Programming Language :: Python :: 3.7
Classifier: Programming Language :: Python :: 3.8
Classifier: Programming Language :: Python :: 3.9
Classifier: Programming Language :: Python :: 3.10
Classifier: Programming Language :: Python :: 3.11
Classifier: Operating System :: OS Independent
Classifier: Intended Audience :: Science/Research
Classifier: Intended Audience :: Developers
Classifier: Natural Language :: English
Classifier: Topic :: Scientific/Engineering
Classifier: Topic :: Software Development :: Libraries
Provides: param
Provides: numbergen
Requires-Python: >=2.7
Provides-Extra: tests
Provides-Extra: doc
Provides-Extra: all
